wandelbots_api_client/__init__.py
wandelbots_api_client/api_client.py
wandelbots_api_client/api_response.py
wandelbots_api_client/authorization.py
wandelbots_api_client/configuration.py
wandelbots_api_client/exceptions.py
wandelbots_api_client/py.typed
wandelbots_api_client/rest.py
wandelbots_api_client/api/__init__.py
wandelbots_api_client/api/application_api.py
wandelbots_api_client/api/cell_api.py
wandelbots_api_client/api/controller_api.py
wandelbots_api_client/api/controller_ios_api.py
wandelbots_api_client/api/coordinate_systems_api.py
wandelbots_api_client/api/device_configuration_api.py
wandelbots_api_client/api/library_program_api.py
wandelbots_api_client/api/library_program_metadata_api.py
wandelbots_api_client/api/library_recipe_api.py
wandelbots_api_client/api/library_recipe_metadata_api.py
wandelbots_api_client/api/license_api.py
wandelbots_api_client/api/motion_api.py
wandelbots_api_client/api/motion_group_api.py
wandelbots_api_client/api/motion_group_infos_api.py
wandelbots_api_client/api/motion_group_jogging_api.py
wandelbots_api_client/api/motion_group_kinematic_api.py
wandelbots_api_client/api/program_api.py
wandelbots_api_client/api/program_operator_api.py
wandelbots_api_client/api/program_values_api.py
wandelbots_api_client/api/store_collision_components_api.py
wandelbots_api_client/api/store_collision_scenes_api.py
wandelbots_api_client/api/store_object_api.py
wandelbots_api_client/api/system_api.py
wandelbots_api_client/api/virtual_robot_api.py
wandelbots_api_client/api/virtual_robot_behavior_api.py
wandelbots_api_client/api/virtual_robot_mode_api.py
wandelbots_api_client/api/virtual_robot_setup_api.py
wandelbots_api_client/models/__init__.py
wandelbots_api_client/models/abb_controller.py
wandelbots_api_client/models/abb_controller_egm_server.py
wandelbots_api_client/models/activate_license_request.py
wandelbots_api_client/models/add_request.py
wandelbots_api_client/models/all_joint_positions_request.py
wandelbots_api_client-25.9.0.dist-info/licenses/LICENSE
wandelbots_api_client-25.9.0.dist-info/METADATA
wandelbots_api_client-25.9.0.dist-info/WHEEL
wandelbots_api_client-25.9.0.dist-info/top_level.txt
wandelbots_api_client-25.9.0.dist-info/RECORD
